LICENSE
MANIFEST.in
README.md
setup.py
cavefinder/__init__.py
cavefinder/finder.py
cavefinder/main.py
cavefinder.egg-info/PKG-INFO
cavefinder.egg-info/SOURCES.txt
cavefinder.egg-info/dependency_links.txt
cavefinder.egg-info/entry_points.txt
cavefinder.egg-info/top_level.txt
cavefinder/support/__init__.py
cavefinder/support/cstruct.py
cavefinder/support/elf.py
cavefinder/support/macho.py
cavefinder/support/mspe.py