Metadata-Version: 2.1
Name: cavefinder
Version: 1.0.0
Summary: Codecave miner
Home-page: https://github.com/jacopodl/cavefinder
Author: Jacopo De Luca
Author-email: jacopo.delu@gmail.com
License: GNU General Public License v3
Keywords: codecave,cave,code,elf,mach-o,portable-executable,injection,code-injection,hacking-tool
Platform: UNKNOWN
Classifier: Development Status :: 5 - Production/Stable
Classifier: Intended Audience :: Developers
Classifier: License :: OSI Approved :: GNU General Public License v3 (GPLv3)
Classifier: Programming Language :: Python :: 3
